qumat/__init__.py
qumat/amazon_braket_backend.py
qumat/cirq_backend.py
qumat/qiskit_backend.py
qumat/qumat.py
qumat-0.0.1.dist-info/LICENSE
qumat-0.0.1.dist-info/METADATA
qumat-0.0.1.dist-info/NOTICE
qumat-0.0.1.dist-info/WHEEL
qumat-0.0.1.dist-info/RECORD
