Metadata-Version: 2.1
Name: qumat
Version: 0.0.1
Summary: A library for composing quantum machine learning.
License: ASFv2
Author: Apache Mahout
Requires-Python: >=3.9,<4.0
Classifier: License :: Other/Proprietary License
Classifier: Programming Language :: Python :: 3
Classifier: Programming Language :: Python :: 3.9
Classifier: Programming Language :: Python :: 3.10
Classifier: Programming Language :: Python :: 3.11
Classifier: Programming Language :: Python :: 3.12
Requires-Dist: amazon-braket-sdk (>=1.10.0,<2.0.0)
Requires-Dist: cirq (>=1.3.0,<2.0.0)
Requires-Dist: qiskit (>=0.45.1,<0.46.0)
Requires-Dist: qiskit-aer (>=0.13.2,<0.14.0)
Requires-Dist: sympy (>=1.9,<2.0)
